vmware_workstation_cli/__init__.py
vmware_workstation_cli/cli.py
vmware_workstation_cli/version.py
vmware_workstation_cli/vmware_workstation_cli.py
vmware_workstation_cli-0.1.2.dist-info/entry_points.txt
vmware_workstation_cli-0.1.2.dist-info/LICENSE
vmware_workstation_cli-0.1.2.dist-info/WHEEL
vmware_workstation_cli-0.1.2.dist-info/METADATA
vmware_workstation_cli-0.1.2.dist-info/RECORD
