Metadata-Version: 2.1
Name: vmware_workstation_cli
Version: 0.1.2
Summary: Top-level package for vmware-workstation-cli.
Keywords: vmware_workstation_cli
Author-email: Matt Krueger <mkrueger@rstms.net>
Classifier: Intended Audience :: Developers
Classifier: Natural Language :: English
Classifier: Programming Language :: Python :: 3
Classifier: Programming Language :: Python :: 3.8
Classifier: Programming Language :: Python :: 3.9
Classifier: Programming Language :: Python :: 3.10
Requires-Dist: click == 8.1.3
Requires-Dist: requests == 2.28.1
Requires-Dist: black==22.3.0 ; extra == "dev"
Requires-Dist: bump2version==1.0.1 ; extra == "dev"
Requires-Dist: coverage==6.4.1 ; extra == "dev"
Requires-Dist: flake8==4.0.1 ; extra == "dev"
Requires-Dist: pytest==7.1.2 ; extra == "dev"
Requires-Dist: tox==3.25.0 ; extra == "dev"
Requires-Dist: sphinx==4.3.2 ; extra == "docs"
Requires-Dist: sphinx-click==3.0.2 ; extra == "docs"
Requires-Dist: sphinx-rtd-theme==1.0.0 ; extra == "docs"
Project-URL: Home, https://github.com/rstms/vmware_workstation_cli
Provides-Extra: dev
Provides-Extra: docs
